aiowirecard/__init__.py
aiowirecard-0.0.7.dist-info/LICENSE.md
aiowirecard-0.0.7.dist-info/METADATA
aiowirecard-0.0.7.dist-info/WHEEL
aiowirecard-0.0.7.dist-info/top_level.txt
aiowirecard-0.0.7.dist-info/RECORD
