Metadata-Version: 2.1
Name: aiowirecard
Version: 0.0.7
Summary: Wirecard API asyncio wrapper
Home-page: https://github.com/jersobh/aiowirecard
Author: jersobh
Author-email: jersobh@gmail.com
License: UNKNOWN
Platform: UNKNOWN
Classifier: Programming Language :: Python :: 3
Classifier: License :: OSI Approved :: MIT License
Classifier: Operating System :: OS Independent
Requires-Dist: aiohttp
